autodistill_mobileclip/__init__.py
autodistill_mobileclip/mobileclip_model.py
autodistill_mobileclip-0.1.0.dist-info/LICENSE
autodistill_mobileclip-0.1.0.dist-info/METADATA
autodistill_mobileclip-0.1.0.dist-info/WHEEL
autodistill_mobileclip-0.1.0.dist-info/top_level.txt
autodistill_mobileclip-0.1.0.dist-info/RECORD
